[{"stnd_dt":"20210520","ticker":"032960","name":"동일기연","chart_url":"https://keulstar.github.io/dnflsmsgkftndlTek1/rec/1.png","dis_url":"https://m.stock.naver.com/item/main.nhn#/stocks/032960/discuss","no":"1","ads":"ca-app-pub-4002117525974192/7740674861"},{"stnd_dt":"20210520","ticker":"042110","name":"에스씨디","chart_url":"https://keulstar.github.io/dnflsmsgkftndlTek1/rec/2.png","dis_url":"https://m.stock.naver.com/item/main.nhn#/stocks/042110/discuss","no":"2","ads":"ca-app-pub-4002117525974192/7173143746"},{"stnd_dt":"20210520","ticker":"060540","name":"에스에이티","chart_url":"https://keulstar.github.io/dnflsmsgkftndlTek1/rec/3.png","dis_url":"https://m.stock.naver.com/item/main.nhn#/stocks/060540/discuss","no":"3","ads":"ca-app-pub-4002117525974192/1056766883"},{"stnd_dt":"20210520","ticker":"189690","name":"포시에스","chart_url":"https://keulstar.github.io/dnflsmsgkftndlTek1/rec/4.png","dis_url":"https://m.stock.naver.com/item/main.nhn#/stocks/189690/discuss","no":"4","ads":"ca-app-pub-4002117525974192/4491140084"}]