[{"index":0,"stnd_dt":"20240311","ticker":"038110","name":"에코플라스틱","chart_url":"https://keulstar.github.io/dnflsmsgkftndlTek1/rec/1.png","dis_url":"https://m.stock.naver.com/item/main.nhn#/stocks/038110/discuss","no":"1","score":2.0,"ads":"ca-app-pub-4002117525974192/7740674861"},{"index":1,"stnd_dt":"20240311","ticker":"204840","name":"지엘팜텍","chart_url":"https://keulstar.github.io/dnflsmsgkftndlTek1/rec/2.png","dis_url":"https://m.stock.naver.com/item/main.nhn#/stocks/204840/discuss","no":"2","score":2.0,"ads":"ca-app-pub-4002117525974192/7173143746"}]