[{"index":1,"stnd_dt":"20240419","ticker":"109610","name":"에스와이","chart_url":"https://keulstar.github.io/dnflsmsgkftndlTek1/rec/2.png","dis_url":"https://m.stock.naver.com/item/main.nhn#/stocks/109610/discuss","no":"2","score":6.0,"ads":"ca-app-pub-4002117525974192/7740674861"},{"index":3,"stnd_dt":"20240419","ticker":"000720","name":"현대건설","chart_url":"https://keulstar.github.io/dnflsmsgkftndlTek1/rec/4.png","dis_url":"https://m.stock.naver.com/item/main.nhn#/stocks/000720/discuss","no":"4","score":5.0,"ads":"ca-app-pub-4002117525974192/7173143746"},{"index":0,"stnd_dt":"20240419","ticker":"022220","name":"TKG애강","chart_url":"https://keulstar.github.io/dnflsmsgkftndlTek1/rec/1.png","dis_url":"https://m.stock.naver.com/item/main.nhn#/stocks/022220/discuss","no":"1","score":3.0,"ads":"ca-app-pub-4002117525974192/1056766883"},{"index":2,"stnd_dt":"20240419","ticker":"079160","name":"CJ CGV","chart_url":"https://keulstar.github.io/dnflsmsgkftndlTek1/rec/3.png","dis_url":"https://m.stock.naver.com/item/main.nhn#/stocks/079160/discuss","no":"3","score":2.0,"ads":"ca-app-pub-4002117525974192/4491140084"}]