[{"index":2,"stnd_dt":"20230911","ticker":"123690","name":"한국화장품","chart_url":"https://keulstar.github.io/dnflsmsgkftndlTek1/rec/3.png","dis_url":"https://m.stock.naver.com/item/main.nhn#/stocks/123690/discuss","no":"3","score":11.0,"ads":"ca-app-pub-4002117525974192/7740674861"},{"index":1,"stnd_dt":"20230911","ticker":"010470","name":"오리콤","chart_url":"https://keulstar.github.io/dnflsmsgkftndlTek1/rec/2.png","dis_url":"https://m.stock.naver.com/item/main.nhn#/stocks/010470/discuss","no":"2","score":9.0,"ads":"ca-app-pub-4002117525974192/7173143746"},{"index":3,"stnd_dt":"20230911","ticker":"008770","name":"호텔신라","chart_url":"https://keulstar.github.io/dnflsmsgkftndlTek1/rec/4.png","dis_url":"https://m.stock.naver.com/item/main.nhn#/stocks/008770/discuss","no":"4","score":3.0,"ads":"ca-app-pub-4002117525974192/1056766883"},{"index":0,"stnd_dt":"20230911","ticker":"050890","name":"쏠리드","chart_url":"https://keulstar.github.io/dnflsmsgkftndlTek1/rec/1.png","dis_url":"https://m.stock.naver.com/item/main.nhn#/stocks/050890/discuss","no":"1","score":2.0,"ads":"ca-app-pub-4002117525974192/4491140084"}]