[{"index":0,"stnd_dt":"20210831","ticker":"073570","name":"WI","chart_url":"https://keulstar.github.io/dnflsmsgkftndlTek1/rec/1.png","dis_url":"https://m.stock.naver.com/item/main.nhn#/stocks/073570/discuss","no":"1","score":5.0,"ads":"ca-app-pub-4002117525974192/7740674861"},{"index":5,"stnd_dt":"20210831","ticker":"011790","name":"SKC","chart_url":"https://keulstar.github.io/dnflsmsgkftndlTek1/rec/6.png","dis_url":"https://m.stock.naver.com/item/main.nhn#/stocks/011790/discuss","no":"6","score":5.0,"ads":"ca-app-pub-4002117525974192/7173143746"},{"index":13,"stnd_dt":"20210831","ticker":"004020","name":"현대제철","chart_url":"https://keulstar.github.io/dnflsmsgkftndlTek1/rec/14.png","dis_url":"https://m.stock.naver.com/item/main.nhn#/stocks/004020/discuss","no":"14","score":5.0,"ads":"ca-app-pub-4002117525974192/1056766883"},{"index":1,"stnd_dt":"20210831","ticker":"144960","name":"뉴파워프라즈마","chart_url":"https://keulstar.github.io/dnflsmsgkftndlTek1/rec/2.png","dis_url":"https://m.stock.naver.com/item/main.nhn#/stocks/144960/discuss","no":"2","score":4.0,"ads":"ca-app-pub-4002117525974192/4491140084"},{"index":4,"stnd_dt":"20210831","ticker":"035420","name":"NAVER","chart_url":"https://keulstar.github.io/dnflsmsgkftndlTek1/rec/5.png","dis_url":"https://m.stock.naver.com/item/main.nhn#/stocks/035420/discuss","no":"5","score":4.0,"ads":"ca-app-pub-4002117525974192/2986486727"},{"index":9,"stnd_dt":"20210831","ticker":"003410","name":"쌍용C&E","chart_url":"https://keulstar.github.io/dnflsmsgkftndlTek1/rec/10.png","dis_url":"https://m.stock.naver.com/item/main.nhn#/stocks/003410/discuss","no":"10","score":4.0,"ads":"ca-app-pub-4002117525974192/9865195198"},{"index":10,"stnd_dt":"20210831","ticker":"122900","name":"아이마켓코리아","chart_url":"https://keulstar.github.io/dnflsmsgkftndlTek1/rec/11.png","dis_url":"https://m.stock.naver.com/item/main.nhn#/stocks/122900/discuss","no":"11","score":4.0,"ads":"ca-app-pub-4002117525974192/7239031858"},{"index":3,"stnd_dt":"20210831","ticker":"041460","name":"한국전자인증","chart_url":"https://keulstar.github.io/dnflsmsgkftndlTek1/rec/4.png","dis_url":"https://m.stock.naver.com/item/main.nhn#/stocks/041460/discuss","no":"4","score":3.0,"ads":"ca-app-pub-4002117525974192/2474339071"},{"index":6,"stnd_dt":"20210831","ticker":"000270","name":"기아","chart_url":"https://keulstar.github.io/dnflsmsgkftndlTek1/rec/7.png","dis_url":"https://m.stock.naver.com/item/main.nhn#/stocks/000270/discuss","no":"7","score":3.0,"ads":"ca-app-pub-4002117525974192/4612868516"},{"index":8,"stnd_dt":"20210831","ticker":"005930","name":"삼성전자","chart_url":"https://keulstar.github.io/dnflsmsgkftndlTek1/rec/9.png","dis_url":"https://m.stock.naver.com/item/main.nhn#/stocks/005930/discuss","no":"9","score":3.0,"ads":"ca-app-pub-4002117525974192/1986705178"},{"index":11,"stnd_dt":"20210831","ticker":"035720","name":"카카오","chart_url":"https://keulstar.github.io/dnflsmsgkftndlTek1/rec/12.png","dis_url":"https://m.stock.naver.com/item/main.nhn#/stocks/035720/discuss","no":"12","score":3.0,"ads":"ca-app-pub-4002117525974192/7173143746"},{"index":2,"stnd_dt":"20210831","ticker":"047310","name":"파워로직스","chart_url":"https://keulstar.github.io/dnflsmsgkftndlTek1/rec/3.png","dis_url":"https://m.stock.naver.com/item/main.nhn#/stocks/047310/discuss","no":"3","score":2.0,"ads":"ca-app-pub-4002117525974192/1056766883"},{"index":7,"stnd_dt":"20210831","ticker":"009150","name":"삼성전기","chart_url":"https://keulstar.github.io/dnflsmsgkftndlTek1/rec/8.png","dis_url":"https://m.stock.naver.com/item/main.nhn#/stocks/009150/discuss","no":"8","score":2.0,"ads":"ca-app-pub-4002117525974192/4491140084"},{"index":12,"stnd_dt":"20210831","ticker":"034830","name":"한국토지신탁","chart_url":"https://keulstar.github.io/dnflsmsgkftndlTek1/rec/13.png","dis_url":"https://m.stock.naver.com/item/main.nhn#/stocks/034830/discuss","no":"13","score":2.0,"ads":"ca-app-pub-4002117525974192/2986486727"}]