[{"index":0,"stnd_dt":"20230508","ticker":"067630","name":"HLB생명과학","chart_url":"https://keulstar.github.io/dnflsmsgkftndlTek1/rec/1.png","dis_url":"https://m.stock.naver.com/item/main.nhn#/stocks/067630/discuss","no":"1","score":4.0,"ads":"ca-app-pub-4002117525974192/7740674861"},{"index":1,"stnd_dt":"20230508","ticker":"061250","name":"화일약품","chart_url":"https://keulstar.github.io/dnflsmsgkftndlTek1/rec/2.png","dis_url":"https://m.stock.naver.com/item/main.nhn#/stocks/061250/discuss","no":"2","score":3.0,"ads":"ca-app-pub-4002117525974192/7173143746"},{"index":2,"stnd_dt":"20230508","ticker":"001740","name":"SK네트웍스","chart_url":"https://keulstar.github.io/dnflsmsgkftndlTek1/rec/3.png","dis_url":"https://m.stock.naver.com/item/main.nhn#/stocks/001740/discuss","no":"3","score":3.0,"ads":"ca-app-pub-4002117525974192/1056766883"},{"index":3,"stnd_dt":"20230508","ticker":"090080","name":"평화산업","chart_url":"https://keulstar.github.io/dnflsmsgkftndlTek1/rec/4.png","dis_url":"https://m.stock.naver.com/item/main.nhn#/stocks/090080/discuss","no":"4","score":3.0,"ads":"ca-app-pub-4002117525974192/4491140084"}]